langgraph_checkpoint_cassandra/__init__.py
langgraph_checkpoint_cassandra/cassandra_saver.py
langgraph_checkpoint_cassandra/migrations.py
langgraph_checkpoint_cassandra/migrations.toml
langgraph_checkpoint_cassandra-0.1.1.dist-info/WHEEL
langgraph_checkpoint_cassandra-0.1.1.dist-info/METADATA
langgraph_checkpoint_cassandra-0.1.1.dist-info/RECORD
