Metadata-Version: 2.4
Name: langgraph-checkpoint-cassandra
Version: 0.1.1
Summary: LangGraph checkpointer for Cassandra
License-Expression: MIT
Requires-Dist: langgraph>=1.0,<2.0
Requires-Dist: cassandra-driver>=3.29.0,<4.0
Requires-Dist: cassandra-asyncio-driver~=0.1.4
Requires-Python: >=3.12
Project-URL: Repository, https://github.com/johntrimble/langgraph-checkpoint-cassandra
